zetl/.schemawiz_config3
zetl/1.CURRENT_DATE.sql
zetl/BMONAS-Finalresend.csv
zetl/__init__.py
zetl/common.py
zetl/local_sqlite_db
zetl/menu.py
zetl/mysql_export.py
zetl/mysql_extract.py
zetl/mysql_import.py
zetl/postgres_export.py
zetl/postgres_extract.py
zetl/postgres_import.py
zetl/run.py
zetl/sample.csv
zetl/sample7.csv
zetl/sqlite_export.py
zetl/sqlite_extract.py
zetl/sqlite_import.py
zetl/view.py
zetl/z.sample8.ddl
zetl/zetl.db
zetl/zetl_this_file.py
zetl/zetl_this_folder.py
zetl/zetl_scripts/etl1/0.init.sql
zetl/zetl_scripts/etl1/10.version_check.sql
zetl/zetl_scripts/etl1/z_etl.csv
zetl/zetl_scripts/etl1 - Copy/0.version_check.sql
zetl/zetl_scripts/etl1 - Copy/z_etl.csv
zetl/zetl_scripts/etl2/0.version_check.sql
zetl/zetl_scripts/etl2/z_etl.csv
zetl/zetl_scripts/etl2 - Copy/0.version_check.sql
zetl/zetl_scripts/etl2 - Copy/z_etl.csv
zetl/zetl_scripts/etl3/0.version_check.sql
zetl/zetl_scripts/etl3/z_etl.csv
zetl/zetl_scripts/etl3 - Copy/0.version_check.sql
zetl/zetl_scripts/etl3 - Copy/z_etl.csv
zetl/zetl_scripts/etl4/0.version_check.sql
zetl/zetl_scripts/etl4/z_etl.csv
zetl/zetl_scripts/etl4 - Copy/0.version_check.sql
zetl/zetl_scripts/etl4 - Copy/z_etl.csv
zetl/zetl_scripts/etl4 - Copy - Copy/0.version_check.sql
zetl/zetl_scripts/etl4 - Copy - Copy/z_etl.csv
zetl/zetl_scripts/etl4 - Copy - Copy (2)/0.version_check.sql
zetl/zetl_scripts/etl4 - Copy - Copy (2)/z_etl.csv
zetl/zetl_scripts/test/1.another_mysqlcheck.sql
zetl/zetl_scripts/test/another_postgrescheck.sql
zetl/zetl_scripts/test/check.sql
zetl/zetl_scripts/test/postgrescheck.sql
zetl/zetl_scripts/test/z_etl.csv
zetl-3.4.1.dist-info/METADATA
zetl-3.4.1.dist-info/WHEEL
zetl-3.4.1.dist-info/licenses/LICENSE
zetl-3.4.1.dist-info/RECORD
