Metadata-Version: 2.3
Name: zetl
Version: 3.4.1
Summary: A simple ETL framework for Python, SQL and BAT files which uses a Postgres database for activity logging.
Project-URL: Homepage, https://github.com/daveskura/zetl
Project-URL: Author Linkedin, https://www.linkedin.com/in/2166883
Author-email: Dave Skura <dskura@gmail.com>
License-File: LICENSE
Classifier: License :: OSI Approved :: MIT License
Classifier: Operating System :: OS Independent
Classifier: Programming Language :: Python :: 3
Requires-Python: >=3.7
Requires-Dist: garbledave-package>=1.0.0
Requires-Dist: mysqldave-package>=1.5.0
Requires-Dist: postgresdave-package>=1.8.0
Requires-Dist: schemawizard-package>=2.5.1
Requires-Dist: sqlitedave-package>=1.3.0
